namescript/__init__.py
namescript/commands.py
namescript/ctp.py
namescript/transpiler.py
namescript/version.py
namescript-2.1.dist-info/LICENSE
namescript-2.1.dist-info/METADATA
namescript-2.1.dist-info/WHEEL
namescript-2.1.dist-info/entry_points.txt
namescript-2.1.dist-info/top_level.txt
namescript-2.1.dist-info/RECORD
