Metadata-Version: 2.1
Name: namescript
Version: 2.1
Summary: Bahasa pemrograman NameScript dengan sintaks Indonesia
Home-page: https://akuzz.my.id/NameScript
Author: AkzDev
Author-email: akzdev.akuzz@gmail.com
Maintainer: AkzDev
Maintainer-email: akzdev.akuzz@gmail.com
License: MIT
Classifier: Programming Language :: Python :: 3
Classifier: License :: OSI Approved :: MIT License
Classifier: Operating System :: OS Independent
Requires-Python: >=3.6
License-File: LICENSE
